jobflow/__init__.py
jobflow/_version.py
jobflow/py.typed
jobflow/settings.py
jobflow/core/__init__.py
jobflow/core/flow.py
jobflow/core/job.py
jobflow/core/maker.py
jobflow/core/reference.py
jobflow/core/schemas.py
jobflow/core/state.py
jobflow/core/store.py
jobflow/managers/__init__.py
jobflow/managers/fireworks.py
jobflow/managers/local.py
jobflow/utils/__init__.py
jobflow/utils/dict_mods.py
jobflow/utils/enum.py
jobflow/utils/find.py
jobflow/utils/graph.py
jobflow/utils/log.py
jobflow/utils/uid.py
jobflow/utils/uuid.py
jobflow-0.2.1.dist-info/licenses/LICENSE
jobflow-0.2.1.dist-info/METADATA
jobflow-0.2.1.dist-info/WHEEL
jobflow-0.2.1.dist-info/top_level.txt
jobflow-0.2.1.dist-info/RECORD
